clkgen.v
module clkgen #(parameter div = 10)(
    input clk ,rst ,
    output logic sclk, tick  
);

reg [$clog2(div)-1:0] counter=0;


always_ff@(posedge clk or posedge rst) begin
    if(rst)begin
    counter<=0;
    sclk<=0;
    tick<=0;
    end
    else if(counter==div/2-1) begin
    counter<=0;
    sclk<=~sclk;
    tick<=1;
    end
    else begin
    tick<=0;
    counter<=counter+1;
    end
end

endmodule


module tb();
parameter N=10;
reg clk,rst;
wire sclk,tick; 
clkgen #(N)uut(.clk(clk),.sclk(sclk),.tick(tick),.rst(rst));
initial clk= 0 ;
always #5 clk = ~clk;
 
initial begin
    $dumpfile("clkgendump.vcd");
    $dumpvars(0, tb);
    $display("Starting simulation...");
    #500;  
    $display("Simulation finished");
    $finish;
end
initial begin
    rst=1; #5;
    rst=0; #5;
end
endmodule

build/clkgendump.vcd
$date
	Thu Jul 02 01:56:02 2026
$end
$version
	Icarus Verilog
$end
$timescale
	1s
$end
$scope module tb $end
$var wire 1 ! tick $end
$var wire 1 " sclk $end
$var reg 1 # clk $end
$var reg 1 $ rst $end
$scope module uut $end
$var wire 1 # clk $end
$var wire 1 $ rst $end
$var reg 4 % counter [3:0] $end
$var reg 1 " sclk $end
$var reg 1 ! tick $end
$upscope $end
$upscope $end
$enddefinitions $end
#0
$dumpvars
b0 %
1$
0#
0"
0!
$end
#5
b1 %
0$
1#
#10
0#
#15
b10 %
1#
#20
0#
#25
b11 %
1#
#30
0#
#35
b100 %
1#
#40
0#
#45
1!
1"
b0 %
1#
#50
0#
#55
b1 %
0!
1#
#60
0#
#65
b10 %
1#
#70
0#
#75
b11 %
1#
#80
0#
#85
b100 %
1#
#90
0#
#95
1!
0"
b0 %
1#
#100
0#
#105
b1 %
0!
1#
#110
0#
#115
b10 %
1#
#120
0#
#125
b11 %
1#
#130
0#
#135
b100 %
1#
#140
0#
#145
1!
1"
b0 %
1#
#150
0#
#155
b1 %
0!
1#
#160
0#
#165
b10 %
1#
#170
0#
#175
b11 %
1#
#180
0#
#185
b100 %
1#
#190
0#
#195
1!
0"
b0 %
1#
#200
0#
#205
b1 %
0!
1#
#210
0#
#215
b10 %
1#
#220
0#
#225
b11 %
1#
#230
0#
#235
b100 %
1#
#240
0#
#245
1!
1"
b0 %
1#
#250
0#
#255
b1 %
0!
1#
#260
0#
#265
b10 %
1#
#270
0#
#275
b11 %
1#
#280
0#
#285
b100 %
1#
#290
0#
#295
1!
0"
b0 %
1#
#300
0#
#305
b1 %
0!
1#
#310
0#
#315
b10 %
1#
#320
0#
#325
b11 %
1#
#330
0#
#335
b100 %
1#
#340
0#
#345
1!
1"
b0 %
1#
#350
0#
#355
b1 %
0!
1#
#360
0#
#365
b10 %
1#
#370
0#
#375
b11 %
1#
#380
0#
#385
b100 %
1#
#390
0#
#395
1!
0"
b0 %
1#
#400
0#
#405
b1 %
0!
1#
#410
0#
#415
b10 %
1#
#420
0#
#425
b11 %
1#
#430
0#
#435
b100 %
1#
#440
0#
#445
1!
1"
b0 %
1#
#450
0#
#455
b1 %
0!
1#
#460
0#
#465
b10 %
1#
#470
0#
#475
b11 %
1#
#480
0#
#485
b100 %
1#
#490
0#
#495
1!
0"
b0 %
1#
