shift_reg_master_spi.v
module spi_master_shift_reg (input clk,rst,tick,load,MISO,en,sclk,
input [7:0] LOAD_data,
output logic MOSI);

logic [7:0] REC_data,SEND_data;

always_ff@(posedge clk or posedge rst) begin

    if(rst)begin
        REC_data<=0;
        SEND_data<=0;
        MOSI<=0;
    end 
    else begin 
        if(load & sclk) begin 
            SEND_data<=LOAD_data;
            MOSI<=0;
        end

        else if(tick & ~sclk & en) begin
            REC_data<={REC_data[6:0],MISO};
            MOSI <= SEND_data[7];
            SEND_data <= {SEND_data[6:0], 1'b0};
        end
    end
end

endmodule

module tb1;

reg clk,rst,tick,load,MISO,en,sclk;
reg [7:0] LOAD_data ;
wire MOSI;
spi_master_shift_reg uut(.clk(clk),.rst(rst),.tick(tick),.load(load),.MISO(MISO),.LOAD_data(LOAD_data),.MOSI(MOSI),.en(en),.sclk(sclk));
initial begin clk= 0 ;
sclk= 0 ;
en=0;
tick=0;
load=0;
LOAD_data=0;
MISO=0;
end

always #5 clk = ~clk;

always begin
    #50 sclk=~sclk;   
    tick=1;
    #10 tick=0;
end

 
initial begin
    $dumpfile("master_shift+regdump.vcd");
    $dumpvars(0, tb1);
    $display("Starting simulation...");
    #2500;  
    $display("Simulation finished");
    $finish;
end
initial begin
    rst=1; #5;
    rst=0; #20;
    LOAD_data=8'b10110111;
    load=1; #50
    load=0;
    en=1;#1000
    en=0;
end
endmodule

build/master_shift+regdump.vcd
$date
	Fri Jul 03 01:39:31 2026
$end
$version
	Icarus Verilog
$end
$timescale
	1s
$end
$scope module tb1 $end
$var wire 1 ! MOSI $end
$var reg 8 " LOAD_data [7:0] $end
$var reg 1 # MISO $end
$var reg 1 $ clk $end
$var reg 1 % en $end
$var reg 1 & load $end
$var reg 1 ' rst $end
$var reg 1 ( sclk $end
$var reg 1 ) tick $end
$scope module uut $end
$var wire 8 * LOAD_data [7:0] $end
$var wire 1 # MISO $end
$var wire 1 $ clk $end
$var wire 1 % en $end
$var wire 1 & load $end
$var wire 1 ' rst $end
$var wire 1 ( sclk $end
$var wire 1 ) tick $end
$var reg 1 ! MOSI $end
$var reg 8 + REC_data [7:0] $end
$var reg 8 , SEND_data [7:0] $end
$upscope $end
$upscope $end
$enddefinitions $end
#0
$dumpvars
b0 ,
b0 +
b0 *
0)
0(
1'
0&
0%
0$
0#
b0 "
0!
$end
#5
0'
1$
#10
0$
#15
1$
#20
0$
#25
1$
1&
b10110111 "
b10110111 *
#30
0$
#35
1$
#40
0$
#45
1$
#50
0$
1)
1(
#55
b10110111 ,
1$
#60
0$
0)
#65
1$
#70
0$
#75
1$
1%
0&
#80
0$
#85
1$
#90
0$
#95
1$
#100
0$
#105
1$
#110
0$
1)
0(
#115
b1101110 ,
1!
1$
#120
0$
0)
#125
1$
#130
0$
#135
1$
#140
0$
#145
1$
#150
0$
#155
1$
#160
0$
#165
1$
#170
0$
1)
1(
#175
1$
#180
0$
0)
#185
1$
#190
0$
#195
1$
#200
0$
#205
1$
#210
0$
#215
1$
#220
0$
#225
1$
#230
0$
1)
0(
#235
b11011100 ,
0!
1$
#240
0$
0)
#245
1$
#250
0$
#255
1$
#260
0$
#265
1$
#270
0$
#275
1$
#280
0$
#285
1$
#290
0$
1)
1(
#295
1$
#300
0$
0)
#305
1$
#310
0$
#315
1$
#320
0$
#325
1$
#330
0$
#335
1$
#340
0$
#345
1$
#350
0$
1)
0(
#355
b10111000 ,
1!
1$
#360
0$
0)
#365
1$
#370
0$
#375
1$
#380
0$
#385
1$
#390
0$
#395
1$
#400
0$
#405
1$
#410
0$
1)
1(
#415
1$
#420
0$
0)
#425
1$
#430
0$
#435
1$
#440
0$
#445
1$
#450
0$
#455
1$
#460
0$
#465
1$
#470
0$
1)
0(
#475
b1110000 ,
1$
#480
0$
0)
#485
1$
#490
0$
#495
1$
#500
0$
#505
1$
#510
0$
#515
1$
#520
0$
#525
1$
#530
0$
1)
1(
#535
1$
#540
0$
0)
#545
1$
#550
0$
#555
1$
#560
0$
#565
1$
#570
0$
#575
1$
#580
0$
#585
1$
#590
0$
1)
0(
#595
b11100000 ,
0!
1$
#600
0$
0)
#605
1$
#610
0$
#615
1$
#620
0$
#625
1$
#630
0$
#635
1$
#640
0$
#645
1$
#650
0$
1)
1(
#655
1$
#660
0$
0)
#665
1$
#670
0$
#675
1$
#680
0$
#685
1$
#690
0$
#695
1$
#700
0$
#705
1$
#710
0$
1)
0(
#715
b11000000 ,
1!
1$
#720
0$
0)
#725
1$
#730
0$
#735
1$
#740
0$
#745
1$
#750
0$
#755
1$
#760
0$
#765
1$
#770
0$
1)
1(
#775
1$
#780
0$
0)
#785
1$
#790
0$
#795
1$
#800
0$
#805
1$
#810
0$
#815
1$
#820
0$
#825
1$
#830
0$
1)
0(
#835
b10000000 ,
1$
#840
0$
0)
#845
1$
#850
0$
#855
1$
#860
0$
#865
1$
#870
0$
#875
1$
#880
0$
#885
1$
#890
0$
1)
1(
#895
1$
#900
0$
0)
#905
1$
#910
0$
#915
1$
#920
0$
#925
1$
#930
0$
#935
1$
#940
0$
#945
1$
#950
0$
1)
0(
#955
b0 ,
1$
#960
0$
0)
#965
1$
#970
0$
#975
1$
#980
0$
#985
1$
#990
0$
#995
1$
#1000
0$
#1005
1$
#1010
0$
1)
1(
#1015
1$
#1020
0$
0)
#1025
1$
#1030
0$
#1035
1$
#1040
0$
#1045
1$
#1050
0$
#1055
1$
#1060
0$
#1065
1$
#1070
0$
1)
0(
#1075
1$
0%
#1080
0$
0)
#1085
1$
#1090
0$
#1095
1$
#1100
0$
#1105
1$
#1110
0$
#1115
1$
#1120
0$
#1125
1$
#1130
0$
1)
1(
#1135
1$
#1140
0$
0)
#1145
1$
#1150
0$
#1155
1$
#1160
0$
#1165
1$
#1170
0$
#1175
1$
#1180
0$
#1185
1$
#1190
0$
1)
0(
#1195
1$
#1200
0$
0)
#1205
1$
#1210
0$
#1215
1$
#1220
0$
#1225
1$
#1230
0$
#1235
1$
#1240
0$
#1245
1$
#1250
0$
1)
1(
#1255
1$
#1260
0$
0)
#1265
1$
#1270
0$
#1275
1$
#1280
0$
#1285
1$
#1290
0$
#1295
1$
#1300
0$
#1305
1$
#1310
0$
1)
0(
#1315
1$
#1320
0$
0)
#1325
1$
#1330
0$
#1335
1$
#1340
0$
#1345
1$
#1350
0$
#1355
1$
#1360
0$
#1365
1$
#1370
0$
1)
1(
#1375
1$
#1380
0$
0)
#1385
1$
#1390
0$
#1395
1$
#1400
0$
#1405
1$
#1410
0$
#1415
1$
#1420
0$
#1425
1$
#1430
0$
1)
0(
#1435
1$
#1440
0$
0)
#1445
1$
#1450
0$
#1455
1$
#1460
0$
#1465
1$
#1470
0$
#1475
1$
#1480
0$
#1485
1$
#1490
0$
1)
1(
#1495
1$
#1500
0$
0)
#1505
1$
#1510
0$
#1515
1$
#1520
0$
#1525
1$
#1530
0$
#1535
1$
#1540
0$
#1545
1$
#1550
0$
1)
0(
#1555
1$
#1560
0$
0)
#1565
1$
#1570
0$
#1575
1$
#1580
0$
#1585
1$
#1590
0$
#1595
1$
#1600
0$
#1605
1$
#1610
0$
1)
1(
#1615
1$
#1620
0$
0)
#1625
1$
#1630
0$
#1635
1$
#1640
0$
#1645
1$
#1650
0$
#1655
1$
#1660
0$
#1665
1$
#1670
0$
1)
0(
#1675
1$
#1680
0$
0)
#1685
1$
#1690
0$
#1695
1$
#1700
0$
#1705
1$
#1710
0$
#1715
1$
#1720
0$
#1725
1$
#1730
0$
1)
1(
#1735
1$
#1740
0$
0)
#1745
1$
#1750
0$
#1755
1$
#1760
0$
#1765
1$
#1770
0$
#1775
1$
#1780
0$
#1785
1$
#1790
0$
1)
0(
#1795
1$
#1800
0$
0)
#1805
1$
#1810
0$
#1815
1$
#1820
0$
#1825
1$
#1830
0$
#1835
1$
#1840
0$
#1845
1$
#1850
0$
1)
1(
#1855
1$
#1860
0$
0)
#1865
1$
#1870
0$
#1875
1$
#1880
0$
#1885
1$
#1890
0$
#1895
1$
#1900
0$
#1905
1$
#1910
0$
1)
0(
#1915
1$
#1920
0$
0)
#1925
1$
#1930
0$
#1935
1$
#1940
0$
#1945
1$
#1950
0$
#1955
1$
#1960
0$
#1965
1$
#1970
0$
1)
1(
#1975
1$
#1980
0$
0)
#1985
1$
#1990
0$
#1995
1$
#2000
0$
#2005
1$
#2010
0$
#2015
1$
#2020
0$
#2025
1$
#2030
0$
1)
0(
#2035
1$
#2040
0$
0)
#2045
1$
#2050
0$
#2055
1$
#2060
0$
#2065
1$
#2070
0$
#2075
1$
#2080
0$
#2085
1$
#2090
0$
1)
1(
#2095
1$
#2100
0$
0)
#2105
1$
#2110
0$
#2115
1$
#2120
0$
#2125
1$
#2130
0$
#2135
1$
#2140
0$
#2145
1$
#2150
0$
1)
0(
#2155
1$
#2160
0$
0)
#2165
1$
#2170
0$
#2175
1$
#2180
0$
#2185
1$
#2190
0$
#2195
1$
#2200
0$
#2205
1$
#2210
0$
1)
1(
#2215
1$
#2220
0$
0)
#2225
1$
#2230
0$
#2235
1$
#2240
0$
#2245
1$
#2250
0$
#2255
1$
#2260
0$
#2265
1$
#2270
0$
1)
0(
#2275
1$
#2280
0$
0)
#2285
1$
#2290
0$
#2295
1$
#2300
0$
#2305
1$
#2310
0$
#2315
1$
#2320
0$
#2325
1$
#2330
0$
1)
1(
#2335
1$
#2340
0$
0)
#2345
1$
#2350
0$
#2355
1$
#2360
0$
#2365
1$
#2370
0$
#2375
1$
#2380
0$
#2385
1$
#2390
0$
1)
0(
#2395
1$
#2400
0$
0)
#2405
1$
#2410
0$
#2415
1$
#2420
0$
#2425
1$
#2430
0$
#2435
1$
#2440
0$
#2445
1$
#2450
0$
1)
1(
#2455
1$
#2460
0$
0)
